covid/__init__.py
covid/api.py
covid/main.py
covid/lib/__init__.py
covid/lib/covid_request.py
covid/lib/errors.py
covid/lib/helper.py
covid/lib/loader.py
covid/model/__init__.py
covid/model/country.py
covid/model/history.py
covid_data_api-1.5.dist-info/LICENSE
covid_data_api-1.5.dist-info/METADATA
covid_data_api-1.5.dist-info/WHEEL
covid_data_api-1.5.dist-info/top_level.txt
covid_data_api-1.5.dist-info/RECORD
