Metadata-Version: 2.1
Name: covid-data-api
Version: 1.5
Summary: 
Home-page: https://github.com/gtkChop/covid19
Author: Swaroop
Author-email: 
License: MIT
Keywords: Data extractor covid19
Platform: UNKNOWN
Classifier: License :: OSI Approved :: MIT License
Classifier: Programming Language :: Python :: 3
Classifier: Programming Language :: Python :: 3.6
Requires-Python: >=3.6
Requires-Dist: python-dateutil (==2.8.1)
Requires-Dist: requests (==2.23.0)
